infranet/__init__.py
infranet/main.py
infranet-0.1.0.dist-info/WHEEL
infranet-0.1.0.dist-info/METADATA
infranet-0.1.0.dist-info/RECORD
