Metadata-Version: 2.1
Name: infranet
Version: 0.1.0
Summary: 
Author: Nishant Yadav
Author-email: nishant.um@gmail.com
Requires-Python: >=3.8,<4.0
Classifier: Programming Language :: Python :: 3
Classifier: Programming Language :: Python :: 3.8
Classifier: Programming Language :: Python :: 3.9
Classifier: Programming Language :: Python :: 3.10
Requires-Dist: networkx (>=2.8.6,<3.0.0)
